src/nebari_plugin_label_studio_chart/__about__.py
src/nebari_plugin_label_studio_chart/__init__.py
src/nebari_plugin_label_studio_chart/plugin.py
src/nebari_plugin_label_studio_chart/template/main.tf
src/nebari_plugin_label_studio_chart/template/outputs.tf
src/nebari_plugin_label_studio_chart/template/variables.tf
src/nebari_plugin_label_studio_chart/template/versions.tf
src/nebari_plugin_label_studio_chart/template/chart/Chart.yaml
src/nebari_plugin_label_studio_chart/template/chart/values.yaml
src/nebari_plugin_label_studio_chart/template/chart/templates/auth.yaml
src/nebari_plugin_label_studio_chart/template/chart/templates/ingress.yaml
nebari_plugin_label_studio_chart-0.0.7.dist-info/METADATA
nebari_plugin_label_studio_chart-0.0.7.dist-info/WHEEL
nebari_plugin_label_studio_chart-0.0.7.dist-info/entry_points.txt
nebari_plugin_label_studio_chart-0.0.7.dist-info/licenses/LICENSE.md
nebari_plugin_label_studio_chart-0.0.7.dist-info/RECORD
